Workbook
Name ExRate: #REF!

Sheet Box Econs_Standard
B2: Exchange rate | C2: 22660
B4: Standard
B5: TC | C5: 189 | E5: Group size/dine in TC | F5: 1.7 | H5: % Dine in | I5: 0.95 | J5: =I5*C5 -> 179.55
B6: AC (inc VAT) | C6: 71000 | E6: Spend per person | F6: =C6/F5 -> 41764.706 | H6: % Take away | I6: =1-I5 -> 0.05 | J6: =I6*C5 -> 9.45
B7: ADS | C7: =C5*C6 -> 13419000 | E7: Dine-in guest count | F7: =J5*F5 -> 305.235
B9: Revenue (excl VAT) | C9: =C7*30 -> 402570000 | E9: Total Capacity
B10: COGS | C10: =C9*C23 -> 124796700 | E10: Size (m2) | F10: 500 | G10: Rent/sqm | H10: 29 | I10: Rent | J10: =120*H10*C2 -> 78856800
B11: Gross profit | C11: =C9-C10 -> 277773300 | E11: BOH | F11: 30
E12: FOH Gross Space | F12: =F10-F11 -> 470
B13: Labor | C13: =SUM(F27) -> 56000000 | E13: FOH Dead Space | F13: 0.05 | G13: Seating area dead space. EG, under stairs, next to pillar
B14: Rent | C14: =J10 -> 78856800 | E14: FOH Net Space | F14: =F12*(1-F13) -> 446.5 | G14: sqm/pax | H14: 1.5 | I14: Seats | J14: =F14/H14 -> 297.66667
B15: Utilities | C15: =C9*C27 -> 24154200
B16: Other Opex | C16: =C9*C28 -> 4025700 | E16: Total Utilized Capacity | F16: 0.7
B17: Marketing | C17: =C9*C29 -> 12077100 | E17: Daypart | F17: Peak time | G17: TC | H17: Guest Count | I17: Turns | J17: Seats
B18: Maintainance | C18: =C9*C30 -> 4025700 | E18: Morning (7 to 11) | F18: 0.3 | G18: =$J$5*F18 -> 53.865 | H18: =G18*$F$5 -> 91.5705 | I18: 2 | J18: =H18/I18/$F$16 -> 65.4075
B19: Reinvestment | C19: =C9*C31 -> 4025700 | E19: Lunch (11:14) | F19: 0.2 | G19: =$J$5*F19 -> 35.91 | H19: =G19*$F$5 -> 61.047 | I19: 2 | J19: =H19/I19/$F$16 -> 43.605
B20: Depreciation | C20: =F32/5/12 -> 42087173 | E20: Tea Time (14:17) | F20: 0.1 | G20: =$J$5*F20 -> 17.955 | H20: =G20*$F$5 -> 30.5235 | I20: 2 | J20: =H20/I20/$F$16 -> 21.8025
B21: EBITDA | C21: =C11-SUM(C13:C19) -> 94608100 | E21: Dinner (17:22) | F21: 0.4 | G21: =$J$5*F21 -> 71.82 | H21: =G21*$F$5 -> 122.094 | I21: 2.2 | J21: =H21/I21/$F$16 -> 79.281818
B23: COGS | C23: 0.31 | E23: Labor | F23: SM/ASM | G23: Cashier | H23: Service | I23: Bar | J23: Security
B24: GM | C24: =1-C23 -> 0.69 | E24: Per shift | F24: 1 | G24: 1 | H24: 1 | I24: 2 | J24: 1
B25: Labor | C25: =C13/C9 -> 0.13910624 | E25: Total Labor Required | F25: 1 | G25: 2 | H25: 2 | I25: 2 | J25: 2
B26: Rent | C26: =C14/C9 -> 0.19588345 | E26: Salary (SIHI included) | F26: 12000000 | G26: 5500000 | H26: 5500000 | I26: 5500000 | J26: 5500000
B27: Utilities(water, electricity, gas, etc) | C27: 0.06 | E27: Monthly Labor | F27: =SUMPRODUCT(F25:J25,F26:J26) -> 56000000
B28: Others OPEX | C28: 0.01
B29: Marketing | C29: 0.03 | E29: Capex
B30: Maintainance | C30: 0.01 | E30: Investment/sqm | F30: 550 | G30: =550*120+60*250 -> 81000 | I30: Pre-opening
B31: Reinvestment | C31: 0.01 | E31: Equipment | G31: 20000 | I31: Rent deposit | J31: =J10*3/C2 -> 10440
B32: Depreciation | C32: =C20/C9 -> 0.10454622 | E32: Total CAPEX | F32: =J32*C2 -> 2525230400 | G32: =G31+G30 -> 101000 | I32: Total Cash needed | J32: =G32+J31+J30 -> 111440
B33: EBITDA | C33: =C21/C9 -> 0.23501031
B34: NOI | C34: =SUM(C33-C32) -> 0.13046408 | E34: Payback | F34: ='Monthly Ramp Up'!S20/(J32*C2) -> 0.44958163 | G34: =(J32*C2)/(C21*12) -> 2.2242902
B36: Break-even Revenue | C36: =SUM(C13:C14)/(1-C23-SUM(C27:C30)) -> 2.3251172e+08
B37: Break-even ADTC | C37: =C36/30/C6 -> 109.16043

Sheet Monthly Ramp Up
B1: Month -5 | C1: Month -4 | D1: Month -3 | E1: Month -2 | F1: Month -1 | G1: Month 01 | H1: Month 02 | I1: Month 03 | J1: Month 04 | K1: Month 05 | L1: Month 06 | M1: Month 07 | N1: Month 08 | O1: Month 09 | P1: Month 10 | Q1: Month 11 | R1: Month 12 | S1: Year 1
B2: 0.5 | C2: 0.6 | D2: 0.7 | E2: 0.8 | F2: 0.9 | G2: 1 | H2: 1 | I2: =H2 -> 1 | J2: =I2 -> 1 | K2: =J2 -> 1 | L2: =K2 -> 1 | M2: =L2 -> 1 | N2: =M2 -> 1 | O2: =N2 -> 1 | P2: =O2 -> 1 | Q2: =P2 -> 1 | R2: =L2 -> 1
A3: Standard
A4: TC | B4: ='Box Econs_Standard'!$C$5*B2 -> 94.5 | C4: ='Box Econs_Standard'!$C$5*C2 -> 113.4 | D4: ='Box Econs_Standard'!$C$5*D2 -> 132.3 | E4: ='Box Econs_Standard'!$C$5*E2 -> 151.2 | F4: ='Box Econs_Standard'!$C$5*F2 -> 170.1 | G4: ='Box Econs_Standard'!$C$5*G2 -> 189 | H4: ='Box Econs_Standard'!$C$5*H2 -> 189 | I4: ='Box Econs_Standard'!$C$5*I2 -> 189 | ... R4: ='Box Econs_Standard'!$C$5*R2 -> 189 | S4: =AVERAGE(G4:R4) -> 189
A5: AC | B5: ='Box Econs_Standard'!C6 -> 71000 | C5: =B5 -> 71000 | D5: =C5 -> 71000 | E5: =D5 -> 71000 | F5: =E5 -> 71000 | G5: =F5 -> 71000 | H5: =G5 -> 71000 | I5: =H5 -> 71000 | J5: =I5 -> 71000 | ... Q5: =P5 -> 71000 | R5: =L5 -> 71000 | S5: =AVERAGE(G5:R5) -> 71000
A6: ADS | B6: =B4*B5 -> 6709500 | C6: =C4*C5 -> 8051400 | D6: =D4*D5 -> 9393300 | E6: =E4*E5 -> 10735200 | F6: =F4*F5 -> 12077100 | G6: =G4*G5 -> 13419000 | H6: =H4*H5 -> 13419000 | I6: =I4*I5 -> 13419000 | ... S6: =S4*S5 -> 13419000
A8: Revenue | B8: ='Box Econs_Standard'!$C$9*'Monthly Ramp Up'!B2 -> 201285000 | C8: ='Box Econs_Standard'!$C$9*'Monthly Ramp Up'!C2 -> 241542000 | D8: ='Box Econs_Standard'!$C$9*'Monthly Ramp Up'!D2 -> 281799000 | E8: ='Box Econs_Standard'!$C$9*'Monthly Ramp Up'!E2 -> 322056000 | F8: ='Box Econs_Standard'!$C$9*'Monthly Ramp Up'!F2 -> 362313000 | G8: ='Box Econs_Standard'!$C$9*'Monthly Ramp Up'!G2 -> 402570000 | H8: ='Box Econs_Standard'!$C$9*'Monthly Ramp Up'!H2 -> 402570000 | I8: ='Box Econs_Standard'!$C$9*'Monthly Ramp Up'!I2 -> 402570000 | ... R8: ='Box Econs_Standard'!$C$9*'Monthly Ramp Up'!R2 -> 402570000 | S8: =SUM(G8:R8) -> 4830840000
A9: COGS | B9: =B8*B22 -> 62398350 | C9: =C8*C22 -> 74878020 | D9: =D8*D22 -> 87357690 | E9: =E8*E22 -> 99837360 | F9: =F8*F22 -> 112317030 | G9: =G8*G22 -> 124796700 | H9: =H8*H22 -> 124796700 | I9: =I8*I22 -> 124796700 | ... R9: =R8*R22 -> 124796700 | S9: =SUM(G9:R9) -> 1497560400
A10: Gross profit | B10: =B8-B9 -> 138886650 | C10: =C8-C9 -> 166663980 | D10: =D8-D9 -> 194441310 | E10: =E8-E9 -> 222218640 | F10: =F8-F9 -> 249995970 | G10: =G8-G9 -> 277773300 | H10: =H8-H9 -> 277773300 | I10: =I8-I9 -> 277773300 | ... S10: =S8-S9 -> 3333279600
A12: Labor | B12: ='Box Econs_Standard'!$C$13 -> 56000000 | C12: =B12 -> 56000000 | D12: =C12 -> 56000000 | E12: =D12 -> 56000000 | F12: =E12 -> 56000000 | G12: =F12 -> 56000000 | H12: =G12 -> 56000000 | I12: =H12 -> 56000000 | J12: =I12 -> 56000000 | ... Q12: =P12 -> 56000000 | R12: =L12 -> 56000000 | S12: =SUM(G12:R12) -> 672000000
A13: Rent | B13: ='Box Econs_Standard'!$C$14 -> 78856800 | C13: =B13 -> 78856800 | D13: =C13 -> 78856800 | E13: =D13 -> 78856800 | F13: =E13 -> 78856800 | G13: =F13 -> 78856800 | H13: =G13 -> 78856800 | I13: =H13 -> 78856800 | J13: =I13 -> 78856800 | ... Q13: =P13 -> 78856800 | R13: =L13 -> 78856800 | S13: =SUM(G13:R13) -> 946281600
A14: Utilities | B14: =B$8*B26 -> 12077100 | C14: =C$8*C26 -> 14492520 | D14: =D$8*D26 -> 16907940 | E14: =E$8*E26 -> 19323360 | F14: =F$8*F26 -> 21738780 | G14: =G$8*G26 -> 24154200 | H14: =H$8*H26 -> 24154200 | I14: =I$8*I26 -> 24154200 | ... R14: =R$8*R26 -> 24154200 | S14: =SUM(G14:R14) -> 289850400
A15: Other Opex | B15: =B$8*B27 -> 2012850 | C15: =C$8*C27 -> 2415420 | D15: =D$8*D27 -> 2817990 | E15: =E$8*E27 -> 3220560 | F15: =F$8*F27 -> 3623130 | G15: =G$8*G27 -> 4025700 | H15: =H$8*H27 -> 4025700 | I15: =I$8*I27 -> 4025700 | ... R15: =R$8*R27 -> 4025700 | S15: =SUM(G15:R15) -> 48308400
A16: Marketing | B16: =B$8*B28 -> 6038550 | C16: =C$8*C28 -> 7246260 | D16: =D$8*D28 -> 8453970 | E16: =E$8*E28 -> 9661680 | F16: =F$8*F28 -> 10869390 | G16: =G$8*G28 -> 12077100 | H16: =H$8*H28 -> 12077100 | I16: =I$8*I28 -> 12077100 | ... R16: =R$8*R28 -> 12077100 | S16: =SUM(G16:R16) -> 144925200
A17: Maintainance | B17: =B$8*B29 -> 2012850 | C17: =C$8*C29 -> 2415420 | D17: =D$8*D29 -> 2817990 | E17: =E$8*E29 -> 3220560 | F17: =F$8*F29 -> 3623130 | G17: =G$8*G29 -> 4025700 | H17: =H$8*H29 -> 4025700 | I17: =I$8*I29 -> 4025700 | ... R17: =R$8*R29 -> 4025700 | S17: =SUM(G17:R17) -> 48308400
A18: Reinvestment | B18: =B$8*B30 -> 2012850 | C18: =C$8*C30 -> 2415420 | D18: =D$8*D30 -> 2817990 | E18: =E$8*E30 -> 3220560 | F18: =F$8*F30 -> 3623130 | G18: =G$8*G30 -> 4025700 | H18: =H$8*H30 -> 4025700 | I18: =I$8*I30 -> 4025700 | ... R18: =R$8*R30 -> 4025700 | S18: =SUM(G18:R18) -> 48308400
A19: Depreciation | B19: ='Box Econs_Standard'!$C$20 -> 42087173 | C19: =B19 -> 42087173 | D19: =C19 -> 42087173 | E19: =D19 -> 42087173 | F19: =E19 -> 42087173 | G19: =F19 -> 42087173 | H19: =G19 -> 42087173 | I19: =H19 -> 42087173 | J19: =I19 -> 42087173 | ... Q19: =P19 -> 42087173 | R19: =L19 -> 42087173 | S19: =SUM(G19:R19) -> 505046080
A20: EBITDA | B20: =B10-SUM(B12:B18) -> -20124350 | C20: =C10-SUM(C12:C18) -> 2822140 | D20: =D10-SUM(D12:D18) -> 25768630 | E20: =E10-SUM(E12:E18) -> 48715120 | F20: =F10-SUM(F12:F18) -> 71661610 | G20: =G10-SUM(G12:G18) -> 94608100 | H20: =H10-SUM(H12:H18) -> 94608100 | I20: =I10-SUM(I12:I18) -> 94608100 | ... S20: =S10-SUM(S12:S18) -> 1135297200
A22: COGS | B22: ='Box Econs_Standard'!$C$23 -> 0.31 | C22: =B22 -> 0.31 | D22: =C22 -> 0.31 | E22: =D22 -> 0.31 | F22: =E22 -> 0.31 | G22: =F22 -> 0.31 | H22: =G22 -> 0.31 | I22: =H22 -> 0.31 | J22: =I22 -> 0.31 | ... S22: =R22 -> 0.31
A23: GM | B23: =1-B22 -> 0.69 | C23: =1-C22 -> 0.69 | D23: =1-D22 -> 0.69 | E23: =1-E22 -> 0.69 | F23: =1-F22 -> 0.69 | G23: =1-G22 -> 0.69 | H23: =1-H22 -> 0.69 | I23: =1-I22 -> 0.69 | ... S23: =1-S22 -> 0.69
A24: Labor | B24: =B12/B8 -> 0.27821248 | C24: =C12/C8 -> 0.23184374 | D24: =D12/D8 -> 0.1987232 | E24: =E12/E8 -> 0.1738828 | F24: =F12/F8 -> 0.15456249 | G24: =G12/G8 -> 0.13910624 | H24: =H12/H8 -> 0.13910624 | I24: =I12/I8 -> 0.13910624 | ... S24: =S12/S8 -> 0.13910624
A25: Rent | B25: =B13/B8 -> 0.3917669 | C25: =C13/C8 -> 0.32647241 | D25: =D13/D8 -> 0.2798335 | E25: =E13/E8 -> 0.24485431 | F25: =F13/F8 -> 0.21764828 | G25: =G13/G8 -> 0.19588345 | H25: =H13/H8 -> 0.19588345 | I25: =I13/I8 -> 0.19588345 | ... S25: =S13/S8 -> 0.19588345
A26: Utilities(water, electricity, gas, etc) | B26: ='Box Econs_Standard'!C27 -> 0.06 | C26: =B26 -> 0.06 | D26: =C26 -> 0.06 | E26: =D26 -> 0.06 | F26: =E26 -> 0.06 | G26: =F26 -> 0.06 | H26: =G26 -> 0.06 | I26: =H26 -> 0.06 | J26: =I26 -> 0.06 | ... R26: =Q26 -> 0.06 | S26: =S14/$S$8 -> 0.06
A27: Others OPEX | B27: ='Box Econs_Standard'!C28 -> 0.01 | C27: =B27 -> 0.01 | D27: =C27 -> 0.01 | E27: =D27 -> 0.01 | F27: =E27 -> 0.01 | G27: =F27 -> 0.01 | H27: =G27 -> 0.01 | I27: =H27 -> 0.01 | J27: =I27 -> 0.01 | ... R27: =Q27 -> 0.01 | S27: =S15/$S$8 -> 0.01
A28: Marketing | B28: ='Box Econs_Standard'!C29 -> 0.03 | C28: =B28 -> 0.03 | D28: =C28 -> 0.03 | E28: =D28 -> 0.03 | F28: =E28 -> 0.03 | G28: =F28 -> 0.03 | H28: =G28 -> 0.03 | I28: =H28 -> 0.03 | J28: =I28 -> 0.03 | ... R28: =Q28 -> 0.03 | S28: =S16/$S$8 -> 0.03
A29: Maintainance | B29: ='Box Econs_Standard'!C30 -> 0.01 | C29: =B29 -> 0.01 | D29: =C29 -> 0.01 | E29: =D29 -> 0.01 | F29: =E29 -> 0.01 | G29: =F29 -> 0.01 | H29: =G29 -> 0.01 | I29: =H29 -> 0.01 | J29: =I29 -> 0.01 | ... R29: =Q29 -> 0.01 | S29: =S17/$S$8 -> 0.01
A30: Reinvestment | B30: ='Box Econs_Standard'!C31 -> 0.01 | C30: =B30 -> 0.01 | D30: =C30 -> 0.01 | E30: =D30 -> 0.01 | F30: =E30 -> 0.01 | G30: =F30 -> 0.01 | H30: =G30 -> 0.01 | I30: =H30 -> 0.01 | J30: =I30 -> 0.01 | ... R30: =Q30 -> 0.01 | S30: =S18/$S$8 -> 0.01
A31: Depreciation | B31: =B19/B8 -> 0.20909245 | C31: =C19/C8 -> 0.17424371 | D31: =D19/D8 -> 0.14935175 | E31: =E19/E8 -> 0.13068278 | F31: =F19/F8 -> 0.11616247 | G31: =G19/G8 -> 0.10454622 | H31: =H19/H8 -> 0.10454622 | I31: =I19/I8 -> 0.10454622 | ... S31: =S19/S8 -> 0.10454622
A32: EBITDA | B32: =B20/B8 -> -0.099979382 | C32: =C20/C8 -> 0.011683848 | D32: =D20/D8 -> 0.091443298 | E32: =E20/E8 -> 0.15126289 | F32: =F20/F8 -> 0.19778923 | G32: =G20/G8 -> 0.23501031 | H32: =H20/H8 -> 0.23501031 | I32: =I20/I8 -> 0.23501031 | ... S32: =S20/S8 -> 0.23501031
A33: NOI | B33: =SUM(B32-B31) -> -0.30907183 | C33: =SUM(C32-C31) -> -0.16255986 | D33: =SUM(D32-D31) -> -0.05790845 | E33: =SUM(E32-E31) -> 0.020580106 | F33: =SUM(F32-F31) -> 0.081626761 | G33: =SUM(G32-G31) -> 0.13046408 | H33: =SUM(H32-H31) -> 0.13046408 | I33: =SUM(I32-I31) -> 0.13046408 | ... S33: =SUM(S32-S31) -> 0.13046408
B36: 0.5 | C36: 0.6 | D36: 0.7 | E36: 0.8 | F36: 0.9 | G36: 1 | H36: 1 | I36: =H36 -> 1 | J36: =I36 -> 1 | K36: =J36 -> 1 | L36: =K36 -> 1 | M36: =L36 -> 1 | N36: =M36 -> 1 | O36: =N36 -> 1 | P36: =O36 -> 1 | Q36: =P36 -> 1 | R36: =L36 -> 1
